tracardi_dot_notation/dict_traverser.py
tracardi_dot_notation/dot_accessor.py
tracardi_dot_notation/dot_template.py
tracardi_dot_notation/utils/singleton.py
tracardi_dot_notation-0.6.7.dist-info/LICENSE.md
tracardi_dot_notation-0.6.7.dist-info/METADATA
tracardi_dot_notation-0.6.7.dist-info/WHEEL
tracardi_dot_notation-0.6.7.dist-info/top_level.txt
tracardi_dot_notation-0.6.7.dist-info/RECORD
